pyChatGPTLoop/Auth0.py
pyChatGPTLoop/__init__.py
pyChatGPTLoop/__main__.py
pyChatGPTLoop/pyChatGPTLoop.py
pyChatGPTLoop-0.1.10.dist-info/LICENSE
pyChatGPTLoop-0.1.10.dist-info/METADATA
pyChatGPTLoop-0.1.10.dist-info/WHEEL
pyChatGPTLoop-0.1.10.dist-info/top_level.txt
pyChatGPTLoop-0.1.10.dist-info/RECORD
