Metadata-Version: 2.1
Name: pyChatGPTLoop
Version: 0.1.10
Summary: Added backtracking chat on the basis of [terry3041/pyChatGPT]
Home-page: https://github.com/nek0us/pyChatGPTLoop
Author: nek0us
Author-email: nekouss@gmail.com
Classifier: Programming Language :: Python :: 3.9
Classifier: License :: OSI Approved :: MIT License
License-File: LICENSE
Requires-Dist: undetected-chromedriver (>=3.2.1)
Requires-Dist: PyVirtualDisplay (>=3.0)
Requires-Dist: markdownify (>=0.11.6)
